xw_base_14.cpython-310-aarch64-linux-gnu.so
xw_base_14-16.0.9.dist-info/METADATA
xw_base_14-16.0.9.dist-info/WHEEL
xw_base_14-16.0.9.dist-info/LICENSE
xw_base_14-16.0.9.dist-info/RECORD
xw_base_14-16.0.9.dist-info/top_level.txt
